hyperialum/__init__.py
hyperialum/hyperialum.py
hyperialum/loop.py
hyperialum/parse.py
hyperialum-1.0.7.dist-info/LICENSE
hyperialum-1.0.7.dist-info/METADATA
hyperialum-1.0.7.dist-info/WHEEL
hyperialum-1.0.7.dist-info/entry_points.txt
hyperialum-1.0.7.dist-info/top_level.txt
hyperialum-1.0.7.dist-info/RECORD
